structLib.py
data_struct-1.2.0.dist-info/LICENSE
data_struct-1.2.0.dist-info/METADATA
data_struct-1.2.0.dist-info/WHEEL
data_struct-1.2.0.dist-info/top_level.txt
data_struct-1.2.0.dist-info/RECORD
