Metadata-Version: 2.1
Name: data-struct
Version: 1.2.0
Summary: A class to help you handling complex JSON-like objects
Home-page: https://github.com/EddieBreeg/structLib
Author: Eddie Breeg
Author-email: eddiebreeg0@protonmail.com
License: GPLv3
Platform: UNKNOWN
Classifier: Development Status :: 5 - Production/Stable
Classifier: Programming Language :: Python :: 3
Classifier: Programming Language :: Python :: 3.8
Classifier: License :: OSI Approved :: GNU General Public License v3 (GPLv3)
Classifier: Operating System :: OS Independent
Requires-Python: >=3.8
Provides-Extra: dev
Requires-Dist: pytest (>=6.0.1) ; extra == 'dev'
